<annotations><filename>CPLX_G0036058.jpg</filename><folder>train</folder><size><width>800</width><height>640</height><depth>3</depth></size><object><name>pothole</name><pose>Unspecified</pose><truncated>0</truncated><difficult>0</difficult><bndbox><xmin>262</xmin><ymin>332</ymin><xmax>271</xmax><ymax>336</ymax></bndbox></object><object><name>pothole</name><pose>Unspecified</pose><truncated>0</truncated><difficult>0</difficult><bndbox><xmin>312</xmin><ymin>347</ymin><xmax>338</xmax><ymax>358</ymax></bndbox></object><object><name>pothole</name><pose>Unspecified</pose><truncated>0</truncated><difficult>0</difficult><bndbox><xmin>406</xmin><ymin>362</ymin><xmax>439</xmax><ymax>384</ymax></bndbox></object></annotations>