<annotations><filename>G0027933.jpg</filename><folder>train</folder><size><width>800</width><height>640</height><depth>3</depth></size><object><name>pothole</name><pose>Unspecified</pose><truncated>0</truncated><difficult>0</difficult><bndbox><xmin>233</xmin><ymin>389</ymin><xmax>264</xmax><ymax>399</ymax></bndbox></object><object><name>pothole</name><pose>Unspecified</pose><truncated>0</truncated><difficult>0</difficult><bndbox><xmin>255</xmin><ymin>400</ymin><xmax>289</xmax><ymax>410</ymax></bndbox></object><object><name>pothole</name><pose>Unspecified</pose><truncated>0</truncated><difficult>0</difficult><bndbox><xmin>388</xmin><ymin>406</ymin><xmax>483</xmax><ymax>416</ymax></bndbox></object><object><name>pothole</name><pose>Unspecified</pose><truncated>0</truncated><difficult>0</difficult><bndbox><xmin>382</xmin><ymin>418</ymin><xmax>482</xmax><ymax>435</ymax></bndbox></object></annotations>